prt_datasets/__init__.py
prt_datasets/base.py
prt_datasets/classification/__init__.py
prt_datasets/classification/mnist.py
prt_datasets/common/__init__.py
prt_datasets/common/conversions.py
prt_datasets/common/utils.py
prt_datasets/detection/__init__.py
prt_datasets/detection/bdd100k.py
prt_datasets/detection/coco.py
prt_datasets/regression/__init__.py
prt_datasets/regression/circle.py
prt_datasets/regression/cubic.py
prt_datasets/regression/thermistor.py
prt_datasets-0.1.1.dist-info/licenses/LICENSE.md
prt_datasets-0.1.1.dist-info/METADATA
prt_datasets-0.1.1.dist-info/WHEEL
prt_datasets-0.1.1.dist-info/top_level.txt
prt_datasets-0.1.1.dist-info/RECORD
