Metadata-Version: 2.4
Name: prt-datasets
Version: 0.1.1
Summary: Add your description here
Requires-Python: >=3.11
License-File: LICENSE.md
Requires-Dist: lightning>=2.5.5
Requires-Dist: numpy>=2.3.3
Requires-Dist: pillow>=11.3.0
Requires-Dist: requests>=2.32.5
Requires-Dist: torch>=2.8.0
Dynamic: license-file
